YehuoRtThreadNeiheShixianYuYingyongKaifaShizhanFix1/README.md
YehuoRtThreadNeiheShixianYuYingyongKaifaShizhanFix1/__init__.py
YehuoRtThreadNeiheShixianYuYingyongKaifaShizhanFix1/__main__.py
YehuoRtThreadNeiheShixianYuYingyongKaifaShizhanFix1/file.epub
YehuoRtThreadNeiheShixianYuYingyongKaifaShizhanFix1/index.html
YehuoRtThreadNeiheShixianYuYingyongKaifaShizhanFix1/css/__init__.py
YehuoRtThreadNeiheShixianYuYingyongKaifaShizhanFix1/css/annotations.css
YehuoRtThreadNeiheShixianYuYingyongKaifaShizhanFix1/css/main.css
YehuoRtThreadNeiheShixianYuYingyongKaifaShizhanFix1/css/normalize.css
YehuoRtThreadNeiheShixianYuYingyongKaifaShizhanFix1/css/popup.css
YehuoRtThreadNeiheShixianYuYingyongKaifaShizhanFix1/font/__init__.py
YehuoRtThreadNeiheShixianYuYingyongKaifaShizhanFix1/font/fontello.eot
YehuoRtThreadNeiheShixianYuYingyongKaifaShizhanFix1/font/fontello.svg
YehuoRtThreadNeiheShixianYuYingyongKaifaShizhanFix1/font/fontello.ttf
YehuoRtThreadNeiheShixianYuYingyongKaifaShizhanFix1/font/fontello.woff
YehuoRtThreadNeiheShixianYuYingyongKaifaShizhanFix1/img/__init__.py
YehuoRtThreadNeiheShixianYuYingyongKaifaShizhanFix1/img/annotator-glyph-sprite.png
YehuoRtThreadNeiheShixianYuYingyongKaifaShizhanFix1/img/annotator-icon-sprite.png
YehuoRtThreadNeiheShixianYuYingyongKaifaShizhanFix1/img/apple-touch-icon.png
YehuoRtThreadNeiheShixianYuYingyongKaifaShizhanFix1/img/cancelfullscreen.png
YehuoRtThreadNeiheShixianYuYingyongKaifaShizhanFix1/img/close.png
YehuoRtThreadNeiheShixianYuYingyongKaifaShizhanFix1/img/fullscreen.png
YehuoRtThreadNeiheShixianYuYingyongKaifaShizhanFix1/img/loader.gif
YehuoRtThreadNeiheShixianYuYingyongKaifaShizhanFix1/img/menu-icon.png
YehuoRtThreadNeiheShixianYuYingyongKaifaShizhanFix1/img/save.png
YehuoRtThreadNeiheShixianYuYingyongKaifaShizhanFix1/img/saved.png
YehuoRtThreadNeiheShixianYuYingyongKaifaShizhanFix1/img/settings-s.png
YehuoRtThreadNeiheShixianYuYingyongKaifaShizhanFix1/img/settings.png
yehuo_rt_thread_neihe_shixian_yu_yingyong_kaifa_shizhan_fix1-2025.3.24.0.dist-info/METADATA
yehuo_rt_thread_neihe_shixian_yu_yingyong_kaifa_shizhan_fix1-2025.3.24.0.dist-info/WHEEL
yehuo_rt_thread_neihe_shixian_yu_yingyong_kaifa_shizhan_fix1-2025.3.24.0.dist-info/entry_points.txt
yehuo_rt_thread_neihe_shixian_yu_yingyong_kaifa_shizhan_fix1-2025.3.24.0.dist-info/top_level.txt
yehuo_rt_thread_neihe_shixian_yu_yingyong_kaifa_shizhan_fix1-2025.3.24.0.dist-info/RECORD
